{
  "kind": "collectionType",
  "collectionName": "accomodation_bookings",
  "info": {
    "singularName": "accomodation-booking",
    "pluralName": "accomodation-bookings",
    "displayName": "Accomodation-Booking",
    "description": ""
  },
  "options": {
    "draftAndPublish": false
  },
  "pluginOptions": {},
  "attributes": {
    "firstName": {
      "type": "string",
      "required": true,
      "unique": false
    },
    "lastName": {
      "type": "string",
      "required": true
    },
    "email": {
      "type": "email",
      "required": true
    },
    "phone": {
      "type": "string",
      "required": true
    },
    "arrivalDate": {
      "type": "date",
      "required": true
    },
    "departureDate": {
      "type": "date",
      "required": true
    },
    "room": {
      "type": "relation",
      "relation": "oneToOne",
      "target": "api::room.room"
    },
    "adults": {
      "type": "integer",
      "required": true
    },
    "children": {
      "type": "integer",
      "required": true
    },
    "specialRequest": {
      "type": "text",
      "required": true
    }
  }
}
